{"header":{"type":"esummary","version":"0.3"},"result":{"uids":["19907645"],"19907645":{"uid":"19907645","pubdate":"2009 Nov 11","epubdate":"2009 Nov 11","source":"PLoS One","authors":[{"name":"Altmann EG","authtype":"Author","clusterid":""},{"name":"Pierrehumbert JB","authtype":"Author","clusterid":""},{"name":"Motter AE","authtype":"Author","clusterid":""}],"lastauthor":"Motter AE","title":"Beyond word frequency: bursts, lulls, and scaling in the temporal distributions of words.","sorttitle":"beyond word frequency bursts lulls and scaling in the temporal distributions of words","volume":"4","issue":"11","pages":"e7678","lang":["eng"],"nlmuniqueid":"101285081","issn":"","essn":"1932-6203","pubtype":["Journal Article","Research Support, Non-U.S. Gov't","Research Support, U.S. Gov't, Non-P.H.S."],"recordstatus":"PubMed - indexed for MEDLINE","pubstatus":"3","articleids":[{"idtype":"pubmed","idtypen":1,"value":"19907645"},{"idtype":"pmc","idtypen":8,"value":"PMC2770836"},{"idtype":"pmcid","idtypen":5,"value":"pmc-id: PMC2770836;"},{"idtype":"doi","idtypen":3,"value":"10.1371/journal.pone.0007678"}],"history":[{"pubstatus":"received","date":"2009/07/09 00:00"},{"pubstatus":"accepted","date":"2009/09/21 00:00"},{"pubstatus":"entrez","date":"2009/11/13 06:00"},{"pubstatus":"pubmed","date":"2009/11/13 06:00"},{"pubstatus":"medline","date":"2010/04/27 06:00"},{"pubstatus":"pmc-release","date":"2009/11/11 00:00"}],"references":[],"attributes":["Has Abstract"],"pmcrefcount":49,"fulljournalname":"PloS one","elocationid":"doi: 10.1371/journal.pone.0007678","doctype":"citation","srccontriblist":[],"booktitle":"","medium":"","edition":"","publisherlocation":"","publishername":"","srcdate":"","reportnumber":"","availablefromurl":"","locationlabel":"","doccontriblist":[],"docdate":"","bookname":"","chapter":"","sortpubdate":"2009/11/11 00:00","sortfirstauthor":"Altmann EG","vernaculartitle":""}}}