{"totalHits":1,"limit":3,"offset":0,"scrollId":"","results":[{"acceptedDate":"","arxivId":null,"authors":[{"name":"Daley, D. J."},{"name":"Carpio, Kristine Joy E."}],"citationCount":0,"contributors":[],"outputs":["https://api.core.ac.uk/v3/outputs/643575921"],"createdDate":"2024-11-19T05:35:05+00:00","dataProviders":[{"id":21592,"name":"Animo Repository - De La Salle University Research","url":"https://api.core.ac.uk/v3/data-providers/21592","logo":"https://api.core.ac.uk/data-providers/21592/logo"}],"depositedDate":"2024-11-19T05:35:05+00:00","abstract":"When {Xn} is an irreducible, stationary, aperiodic Markov chain on the countable state space X = {i, j,…}, the study of long-range dependence of any square integrable functional {Yn} := {yXn} of the chain, for any real-valued function {yi: i ∈ X}, involves in an essential manner the functions Qijn = ∑r=1n(pijr − πj), where pijr = P{Xr = j | X0 = i} is the r-step transition probability for the chain and {πi: i ∈ X} = P{Xn = i} is the stationary distribution for {Xn}. The simplest functional arises when Yn is the indicator sequence for visits to some particular state i, Ini = I{Xn=i} say, in which case limsupn→∞n−1var(Y1 + ∙ ∙ ∙ + Yn) = limsupn→∞n−1 var(Ni(0, n]) = ∞ if and only if the generic return time random variable Tii for the chain to return to state i starting from i has infinite second moment (here, Ni(0, n] denotes the number of visits of Xr to state i in the time epochs {1,…,n}). This condition is equivalent to Qjin → ∞ for one (and then every) state j, or to E(Tjj2) = ∞ for one (and then every) state j, and when it holds, (Qijn / πj) / (Qkkn / πk) → 1 for n → ∞ for any triplet of states i, jk","documentType":"","doi":"10.1239/jap/1197908823","downloadUrl":"","fieldOfStudy":"text","fullText":"Not available for public API users.","id":168352240,"identifiers":[{"identifier":"643575921","type":"core_id"},{"identifier":"10.1239/jap/1197908823","type":"doi"},{"identifier":"oai:animorepository.dlsu.edu.ph:faculty_research-15197","type":"oai_id"},{"identifier":"oai:animorepository.dlsu.edu.ph:faculty_research-15197","type":"oai"}],"title":"Long-range dependence of Markov chains in discrete time on countable state space","magId":null,"oaiIds":["oai:animorepository.dlsu.edu.ph:faculty_research-15197"],"publishedDate":"","publisher":"","pubmedId":null,"references":[],"sourceFulltextUrls":[],"updatedDate":"","yearPublished":2007,"journals":[],"links":[{"type":"display","url":"https://core.ac.uk/works/168352240"}]}],"searchId":"937835f430121bdb75a3aff6f63c1d73"}