{"id":"https://openalex.org/W2013701106","doi":"https://doi.org/10.1145/269790.269792","title":"Fast, approximate synthesis of fractional Gaussian noise for generating self-similar network traffic","display_name":"Fast, approximate synthesis of fractional Gaussian noise for generating self-similar network traffic","publication_year":1997,"publication_date":"1997-10-01","ids":{"openalex":"https://openalex.org/W2013701106","doi":"https://doi.org/10.1145/269790.269792","mag":"2013701106"},"language":"en","primary_location":{"id":"doi:10.1145/269790.269792","is_oa":false,"landing_page_url":"https://doi.org/10.1145/269790.269792","pdf_url":null,"source":{"id":"https://openalex.org/S66039016","display_name":"ACM SIGCOMM Computer Communication Review","issn_l":"0146-4833","issn":["0146-4833","1943-5819"],"is_oa":false,"is_in_doaj":false,"is_core":true,"host_organization":"https://openalex.org/P4310319798","host_organization_name":"Association for Computing Machinery","host_organization_lineage":["https://openalex.org/P4310319798"],"host_organization_lineage_names":["Association for Computing Machinery"],"type":"journal"},"license":null,"license_id":null,"version":"publishedVersion","is_accepted":true,"is_published":true,"raw_source_name":"ACM SIGCOMM Computer Communication Review","raw_type":"journal-article"},"type":"article","indexed_in":["crossref"],"open_access":{"is_oa":false,"oa_status":"closed","oa_url":null,"any_repository_has_fulltext":false},"authorships":[{"author_position":"first","author":{"id":"https://openalex.org/A5002219113","display_name":"Vern Paxson","orcid":"https://orcid.org/0009-0005-2673-543X"},"institutions":[{"id":"https://openalex.org/I148283060","display_name":"Lawrence Berkeley National Laboratory","ror":"https://ror.org/02jbv0t02","country_code":"US","type":"facility","lineage":["https://openalex.org/I1330989302","https://openalex.org/I148283060","https://openalex.org/I39565521"]}],"countries":["US"],"is_corresponding":true,"raw_author_name":"Vern Paxson","raw_affiliation_strings":["Network Research Group, Lawrence Berkeley National Laboratory, 1 Cyclotron Road, Berkeley, CA","Network Research Group, Lawrence Berkeley National Laboratory, 1 Cyclotron Road, Berkeley, CA#TAB#"],"raw_orcid":null,"affiliations":[{"raw_affiliation_string":"Network Research Group, Lawrence Berkeley National Laboratory, 1 Cyclotron Road, Berkeley, CA","institution_ids":["https://openalex.org/I148283060"]},{"raw_affiliation_string":"Network Research Group, Lawrence Berkeley National Laboratory, 1 Cyclotron Road, Berkeley, CA#TAB#","institution_ids":["https://openalex.org/I148283060"]}]}],"institutions":[],"countries_distinct_count":1,"institutions_distinct_count":1,"corresponding_author_ids":["https://openalex.org/A5002219113"],"corresponding_institution_ids":["https://openalex.org/I148283060"],"apc_list":null,"apc_paid":null,"fwci":7.8498,"has_fulltext":false,"cited_by_count":423,"citation_normalized_percentile":{"value":0.98160494,"is_in_top_1_percent":false,"is_in_top_10_percent":true},"cited_by_percentile_year":{"min":91,"max":100},"biblio":{"volume":"27","issue":"5","first_page":"5","last_page":"18"},"is_retracted":false,"is_paratext":false,"is_xpac":false,"primary_topic":{"id":"https://openalex.org/T10064","display_name":"Complex Network Analysis Techniques","score":0.9968000054359436,"subfield":{"id":"https://openalex.org/subfields/3109","display_name":"Statistical and Nonlinear Physics"},"field":{"id":"https://openalex.org/fields/31","display_name":"Physics and Astronomy"},"domain":{"id":"https://openalex.org/domains/3","display_name":"Physical Sciences"}},"topics":[{"id":"https://openalex.org/T10064","display_name":"Complex Network Analysis Techniques","score":0.9968000054359436,"subfield":{"id":"https://openalex.org/subfields/3109","display_name":"Statistical and Nonlinear Physics"},"field":{"id":"https://openalex.org/fields/31","display_name":"Physics and Astronomy"},"domain":{"id":"https://openalex.org/domains/3","display_name":"Physical Sciences"}},{"id":"https://openalex.org/T11270","display_name":"Complex Systems and Time Series Analysis","score":0.996399998664856,"subfield":{"id":"https://openalex.org/subfields/2002","display_name":"Economics and Econometrics"},"field":{"id":"https://openalex.org/fields/20","display_name":"Economics, Econometrics and Finance"},"domain":{"id":"https://openalex.org/domains/2","display_name":"Social Sciences"}},{"id":"https://openalex.org/T11152","display_name":"Stochastic processes and statistical mechanics","score":0.9945999979972839,"subfield":{"id":"https://openalex.org/subfields/2610","display_name":"Mathematical Physics"},"field":{"id":"https://openalex.org/fields/26","display_name":"Mathematics"},"domain":{"id":"https://openalex.org/domains/3","display_name":"Physical Sciences"}}],"keywords":[{"id":"https://openalex.org/keywords/hurst-exponent","display_name":"Hurst exponent","score":0.878825306892395},{"id":"https://openalex.org/keywords/computer-science","display_name":"Computer science","score":0.7448466420173645},{"id":"https://openalex.org/keywords/estimator","display_name":"Estimator","score":0.7128835916519165},{"id":"https://openalex.org/keywords/noise","display_name":"Noise (video)","score":0.5715683698654175},{"id":"https://openalex.org/keywords/range","display_name":"Range (aeronautics)","score":0.5674181580543518},{"id":"https://openalex.org/keywords/sample","display_name":"Sample (material)","score":0.5525192022323608},{"id":"https://openalex.org/keywords/gaussian-noise","display_name":"Gaussian noise","score":0.5417386293411255},{"id":"https://openalex.org/keywords/poisson-distribution","display_name":"Poisson distribution","score":0.5347949862480164},{"id":"https://openalex.org/keywords/algorithm","display_name":"Algorithm","score":0.5260041952133179},{"id":"https://openalex.org/keywords/gaussian","display_name":"Gaussian","score":0.5139390826225281},{"id":"https://openalex.org/keywords/fractional-brownian-motion","display_name":"Fractional Brownian motion","score":0.45073947310447693},{"id":"https://openalex.org/keywords/gaussian-process","display_name":"Gaussian process","score":0.4370117485523224},{"id":"https://openalex.org/keywords/self-similarity","display_name":"Self-similarity","score":0.4356363117694855},{"id":"https://openalex.org/keywords/process","display_name":"Process (computing)","score":0.4143935441970825},{"id":"https://openalex.org/keywords/series","display_name":"Series (stratigraphy)","score":0.41378504037857056},{"id":"https://openalex.org/keywords/fourier-transform","display_name":"Fourier transform","score":0.41185706853866577},{"id":"https://openalex.org/keywords/applied-mathematics","display_name":"Applied mathematics","score":0.37125349044799805},{"id":"https://openalex.org/keywords/mathematics","display_name":"Mathematics","score":0.19082090258598328},{"id":"https://openalex.org/keywords/statistics","display_name":"Statistics","score":0.16423195600509644},{"id":"https://openalex.org/keywords/artificial-intelligence","display_name":"Artificial intelligence","score":0.12703678011894226},{"id":"https://openalex.org/keywords/brownian-motion","display_name":"Brownian motion","score":0.10752463340759277},{"id":"https://openalex.org/keywords/mathematical-analysis","display_name":"Mathematical analysis","score":0.10536587238311768}],"concepts":[{"id":"https://openalex.org/C96835011","wikidata":"https://www.wikidata.org/wiki/Q1638718","display_name":"Hurst exponent","level":2,"score":0.878825306892395},{"id":"https://openalex.org/C41008148","wikidata":"https://www.wikidata.org/wiki/Q21198","display_name":"Computer science","level":0,"score":0.7448466420173645},{"id":"https://openalex.org/C185429906","wikidata":"https://www.wikidata.org/wiki/Q1130160","display_name":"Estimator","level":2,"score":0.7128835916519165},{"id":"https://openalex.org/C99498987","wikidata":"https://www.wikidata.org/wiki/Q2210247","display_name":"Noise (video)","level":3,"score":0.5715683698654175},{"id":"https://openalex.org/C204323151","wikidata":"https://www.wikidata.org/wiki/Q905424","display_name":"Range (aeronautics)","level":2,"score":0.5674181580543518},{"id":"https://openalex.org/C198531522","wikidata":"https://www.wikidata.org/wiki/Q485146","display_name":"Sample (material)","level":2,"score":0.5525192022323608},{"id":"https://openalex.org/C4199805","wikidata":"https://www.wikidata.org/wiki/Q2725903","display_name":"Gaussian noise","level":2,"score":0.5417386293411255},{"id":"https://openalex.org/C100906024","wikidata":"https://www.wikidata.org/wiki/Q205692","display_name":"Poisson distribution","level":2,"score":0.5347949862480164},{"id":"https://openalex.org/C11413529","wikidata":"https://www.wikidata.org/wiki/Q8366","display_name":"Algorithm","level":1,"score":0.5260041952133179},{"id":"https://openalex.org/C163716315","wikidata":"https://www.wikidata.org/wiki/Q901177","display_name":"Gaussian","level":2,"score":0.5139390826225281},{"id":"https://openalex.org/C108819105","wikidata":"https://www.wikidata.org/wiki/Q1143293","display_name":"Fractional Brownian motion","level":3,"score":0.45073947310447693},{"id":"https://openalex.org/C61326573","wikidata":"https://www.wikidata.org/wiki/Q1496376","display_name":"Gaussian process","level":3,"score":0.4370117485523224},{"id":"https://openalex.org/C119453123","wikidata":"https://www.wikidata.org/wiki/Q262372","display_name":"Self-similarity","level":2,"score":0.4356363117694855},{"id":"https://openalex.org/C98045186","wikidata":"https://www.wikidata.org/wiki/Q205663","display_name":"Process (computing)","level":2,"score":0.4143935441970825},{"id":"https://openalex.org/C143724316","wikidata":"https://www.wikidata.org/wiki/Q312468","display_name":"Series (stratigraphy)","level":2,"score":0.41378504037857056},{"id":"https://openalex.org/C102519508","wikidata":"https://www.wikidata.org/wiki/Q6520159","display_name":"Fourier transform","level":2,"score":0.41185706853866577},{"id":"https://openalex.org/C28826006","wikidata":"https://www.wikidata.org/wiki/Q33521","display_name":"Applied mathematics","level":1,"score":0.37125349044799805},{"id":"https://openalex.org/C33923547","wikidata":"https://www.wikidata.org/wiki/Q395","display_name":"Mathematics","level":0,"score":0.19082090258598328},{"id":"https://openalex.org/C105795698","wikidata":"https://www.wikidata.org/wiki/Q12483","display_name":"Statistics","level":1,"score":0.16423195600509644},{"id":"https://openalex.org/C154945302","wikidata":"https://www.wikidata.org/wiki/Q11660","display_name":"Artificial intelligence","level":1,"score":0.12703678011894226},{"id":"https://openalex.org/C112401455","wikidata":"https://www.wikidata.org/wiki/Q178036","display_name":"Brownian motion","level":2,"score":0.10752463340759277},{"id":"https://openalex.org/C134306372","wikidata":"https://www.wikidata.org/wiki/Q7754","display_name":"Mathematical analysis","level":1,"score":0.10536587238311768},{"id":"https://openalex.org/C111919701","wikidata":"https://www.wikidata.org/wiki/Q9135","display_name":"Operating system","level":1,"score":0},{"id":"https://openalex.org/C121332964","wikidata":"https://www.wikidata.org/wiki/Q413","display_name":"Physics","level":0,"score":0},{"id":"https://openalex.org/C151730666","wikidata":"https://www.wikidata.org/wiki/Q7205","display_name":"Paleontology","level":1,"score":0},{"id":"https://openalex.org/C62520636","wikidata":"https://www.wikidata.org/wiki/Q944","display_name":"Quantum mechanics","level":1,"score":0},{"id":"https://openalex.org/C43617362","wikidata":"https://www.wikidata.org/wiki/Q170050","display_name":"Chromatography","level":1,"score":0},{"id":"https://openalex.org/C159985019","wikidata":"https://www.wikidata.org/wiki/Q181790","display_name":"Composite material","level":1,"score":0},{"id":"https://openalex.org/C86803240","wikidata":"https://www.wikidata.org/wiki/Q420","display_name":"Biology","level":0,"score":0},{"id":"https://openalex.org/C2524010","wikidata":"https://www.wikidata.org/wiki/Q8087","display_name":"Geometry","level":1,"score":0},{"id":"https://openalex.org/C192562407","wikidata":"https://www.wikidata.org/wiki/Q228736","display_name":"Materials science","level":0,"score":0},{"id":"https://openalex.org/C185592680","wikidata":"https://www.wikidata.org/wiki/Q2329","display_name":"Chemistry","level":0,"score":0},{"id":"https://openalex.org/C115961682","wikidata":"https://www.wikidata.org/wiki/Q860623","display_name":"Image (mathematics)","level":2,"score":0}],"mesh":[],"locations_count":3,"locations":[{"id":"doi:10.1145/269790.269792","is_oa":false,"landing_page_url":"https://doi.org/10.1145/269790.269792","pdf_url":null,"source":{"id":"https://openalex.org/S66039016","display_name":"ACM SIGCOMM Computer Communication Review","issn_l":"0146-4833","issn":["0146-4833","1943-5819"],"is_oa":false,"is_in_doaj":false,"is_core":true,"host_organization":"https://openalex.org/P4310319798","host_organization_name":"Association for Computing Machinery","host_organization_lineage":["https://openalex.org/P4310319798"],"host_organization_lineage_names":["Association for Computing Machinery"],"type":"journal"},"license":null,"license_id":null,"version":"publishedVersion","is_accepted":true,"is_published":true,"raw_source_name":"ACM SIGCOMM Computer Communication Review","raw_type":"journal-article"},{"id":"pmh:oai:CiteSeerX.psu:10.1.1.342.2422","is_oa":false,"landing_page_url":"http://citeseerx.ist.psu.edu/viewdoc/summary?doi=10.1.1.342.2422","pdf_url":null,"source":null,"license":null,"license_id":null,"version":"submittedVersion","is_accepted":false,"is_published":false,"raw_source_name":"http://arxiv.org/pdf/cs/9809030v1.pdf","raw_type":"text"},{"id":"pmh:oai:CiteSeerX.psu:10.1.1.54.9715","is_oa":false,"landing_page_url":"http://citeseerx.ist.psu.edu/viewdoc/summary?doi=10.1.1.54.9715","pdf_url":null,"source":null,"license":null,"license_id":null,"version":"submittedVersion","is_accepted":false,"is_published":false,"raw_source_name":"ftp://ftp.ee.lbl.gov/papers/vp-FGN-CCR.ps.Z","raw_type":"text"}],"best_oa_location":null,"sustainable_development_goals":[],"awards":[],"funders":[],"has_content":{"grobid_xml":false,"pdf":false},"content_urls":null,"referenced_works_count":27,"referenced_works":["https://openalex.org/W168449061","https://openalex.org/W1512573266","https://openalex.org/W1563063445","https://openalex.org/W1971536848","https://openalex.org/W1981136151","https://openalex.org/W1994022456","https://openalex.org/W2019853444","https://openalex.org/W2022894179","https://openalex.org/W2049742719","https://openalex.org/W2062962812","https://openalex.org/W2065175568","https://openalex.org/W2069726457","https://openalex.org/W2102616700","https://openalex.org/W2103312864","https://openalex.org/W2104314879","https://openalex.org/W2105818147","https://openalex.org/W2115122866","https://openalex.org/W2122889548","https://openalex.org/W2122923407","https://openalex.org/W2136021618","https://openalex.org/W2148275477","https://openalex.org/W2158712333","https://openalex.org/W2159048618","https://openalex.org/W2165773639","https://openalex.org/W2171873915","https://openalex.org/W2751862591","https://openalex.org/W4251625132"],"related_works":["https://openalex.org/W2915158306","https://openalex.org/W2364010220","https://openalex.org/W26397136","https://openalex.org/W3010725710","https://openalex.org/W2401810189","https://openalex.org/W3001803811","https://openalex.org/W2012792015","https://openalex.org/W2087458835","https://openalex.org/W3047008523","https://openalex.org/W3021897514"],"abstract_inverted_index":{"Recent":[0],"network":[1,6,108],"traffic":[2],"studies":[3],"argue":[4],"that":[5,74],"arrival":[7],"processes":[8,17,22],"are":[9],"much":[10],"more":[11],"faithfully":[12],"modeled":[13],"using":[14,101],"statistically":[15],"self-similar":[16,30,42,54,61,93,141],"instead":[18],"of":[19,60,123,135],"traditional":[20],"Poisson":[21],"[LTWW94,":[23],"PF95].":[24],"One":[25],"difficulty":[26],"in":[27,100,139],"dealing":[28],"with":[29],"models":[31],"is":[32,77],"how":[33,111],"to":[34,41,87,91],"efficiently":[35],"synthesize":[36],"traces":[37],"(sample":[38],"paths)":[39],"corresponding":[40],"traffic.":[43],"We":[44,72,96],"present":[45,138],"a":[46,140],"fast":[47,79],"Fourier":[48],"transform":[49],"method":[50,76,117],"for":[51,57,106,126],"synthesizing":[52],"approximate":[53],"sample":[55,94,104],"paths":[56,105],"one":[58],"type":[59],"process,":[62],"Fractional":[63],"Gaussian":[64],"Noise,":[65],"and":[66,70,85,110],"assess":[67],"its":[68],"performance":[69],"validity.":[71],"find":[73],"the":[75,129,133],"as":[78],"or":[80],"faster":[81],"than":[82],"existing":[83],"methods":[84],"appears":[86],"generate":[88],"close":[89],"approximations":[90],"true":[92],"paths.":[95],"also":[97],"discuss":[98],"issues":[99],"such":[102],"synthesized":[103],"simulating":[107],"traffic,":[109],"an":[112],"approximation":[113],"used":[114],"by":[115],"our":[116],"can":[118],"dramatically":[119],"speed":[120],"up":[121],"evaluation":[122],"Whittle's":[124],"estimator":[125],"H":[127],",":[128],"Hurst":[130],"parameter":[131],"giving":[132],"strength":[134],"long-range":[136],"dependence":[137],"time":[142],"series.":[143]},"counts_by_year":[{"year":2025,"cited_by_count":1},{"year":2024,"cited_by_count":5},{"year":2023,"cited_by_count":3},{"year":2022,"cited_by_count":10},{"year":2021,"cited_by_count":7},{"year":2020,"cited_by_count":7},{"year":2019,"cited_by_count":8},{"year":2018,"cited_by_count":10},{"year":2017,"cited_by_count":8},{"year":2016,"cited_by_count":11},{"year":2015,"cited_by_count":17},{"year":2014,"cited_by_count":10},{"year":2013,"cited_by_count":13},{"year":2012,"cited_by_count":12}],"updated_date":"2026-05-21T06:26:12.895304","created_date":"2025-10-10T00:00:00"}