{"best_oa_location":null,"data_standard":2,"doi":"10.1145/2674005.2675012","doi_url":"https://doi.org/10.1145/2674005.2675012","first_oa_location":null,"genre":"proceedings-article","has_repository_copy":false,"is_oa":false,"is_paratext":false,"journal_is_in_doaj":null,"journal_is_oa":false,"journal_issn_l":null,"journal_issns":null,"journal_name":"Proceedings of the 10th ACM International on Conference on emerging Networking Experiments and Technologies","oa_locations":[],"oa_locations_embargoed":[],"oa_status":"closed","published_date":"2014-12-02","publisher":"ACM","title":"COLD","updated":"2025-05-22T18:42:22Z","year":2014,"z_authors":[{"author_position":"first","is_corresponding":true,"raw_affiliation_strings":["University of Adelaide, Adelaide, Australia"],"raw_author_name":"Rhys Bowden"},{"author_position":"additional","is_corresponding":false,"raw_affiliation_strings":["University of Adelaide, Adelaide, Australia"],"raw_author_name":"Matthew Roughan"},{"author_position":"last","is_corresponding":false,"raw_affiliation_strings":["University of Adelaide, Adelaide, Australia"],"raw_author_name":"Nigel Bean"}]}